[{"address_components":[{"long_name":"Hocalar","short_name":"Hocalar","types":["locality","political"]},{"long_name":"Hocalar","short_name":"Hocalar","types":["administrative_area_level_2","political"]},{"long_name":"Afyonkarahisar","short_name":"Afyonkarahisar","types":["administrative_area_level_1","political"]},{"long_name":"Turkey","short_name":"TR","types":["country","political"]}],"formatted_address":"Hocalar, Afyonkarahisar, Turkey","geometry":{"bounds":{"northeast":{"lat":38.586599,"lng":29.973306},"southwest":{"lat":38.5692661,"lng":29.9603911}},"location":{"lat":38.576673,"lng":29.969668},"location_type":"APPROXIMATE","viewport":{"northeast":{"lat":38.586599,"lng":29.973306},"southwest":{"lat":38.5692661,"lng":29.9603911}}},"place_id":"ChIJ5z53y_mlyBQRKlfpxTtBTQ0","types":["locality","political"]}]