[{"address_components":[{"long_name":"Hamur","short_name":"Hamur","types":["administrative_area_level_2","political"]},{"long_name":"Ağrı","short_name":"Ağrı","types":["administrative_area_level_1","political"]},{"long_name":"Turkey","short_name":"TR","types":["country","political"]}],"formatted_address":"Hamur/Ağrı, Turkey","geometry":{"bounds":{"northeast":{"lat":39.668371,"lng":43.28031},"southwest":{"lat":39.322092,"lng":42.87984}},"location":{"lat":39.4672359,"lng":43.1108921},"location_type":"APPROXIMATE","viewport":{"northeast":{"lat":39.668371,"lng":43.28031},"southwest":{"lat":39.322092,"lng":42.87984}}},"partial_match":true,"place_id":"ChIJJxjwc4mVbEAR3b11feHj_jg","types":["administrative_area_level_2","political"]}]