[{"address_components":[{"long_name":"Hasköy","short_name":"Hasköy","types":["administrative_area_level_4","political"]},{"long_name":"Keçiören","short_name":"Keçiören","types":["administrative_area_level_2","political"]},{"long_name":"Ankara","short_name":"Ankara","types":["administrative_area_level_1","political"]},{"long_name":"Turkey","short_name":"TR","types":["country","political"]}],"formatted_address":"Hasköy, Keçiören/Ankara, Turkey","geometry":{"bounds":{"northeast":{"lat":39.97874789999999,"lng":32.885667},"southwest":{"lat":39.97107099999999,"lng":32.8756099}},"location":{"lat":39.9747026,"lng":32.8810642},"location_type":"APPROXIMATE","viewport":{"northeast":{"lat":39.97874789999999,"lng":32.885667},"southwest":{"lat":39.97107099999999,"lng":32.8756099}}},"place_id":"ChIJFye-3JZN0xQRIGIyUNRauKU","types":["administrative_area_level_4","political"]}]