[{"address_components":[{"long_name":"Güdül","short_name":"Güdül","types":["locality","political"]},{"long_name":"Güdül","short_name":"Güdül","types":["administrative_area_level_2","political"]},{"long_name":"Ankara","short_name":"Ankara","types":["administrative_area_level_1","political"]},{"long_name":"Turkey","short_name":"TR","types":["country","political"]}],"formatted_address":"Güdül, Ankara, Turkey","geometry":{"bounds":{"northeast":{"lat":40.219718,"lng":32.2608351},"southwest":{"lat":40.204686,"lng":32.236546}},"location":{"lat":40.210512,"lng":32.24553},"location_type":"APPROXIMATE","viewport":{"northeast":{"lat":40.219718,"lng":32.2608351},"southwest":{"lat":40.204686,"lng":32.236546}}},"place_id":"ChIJ2YLgKkHT0hQRHIP0uQi6Nkg","types":["locality","political"]}]