[{"address_components":[{"long_name":"Meydankavağı","short_name":"Meydankavağı","types":["administrative_area_level_4","political"]},{"long_name":"Muratpaşa","short_name":"Muratpaşa","types":["administrative_area_level_2","political"]},{"long_name":"Antalya","short_name":"Antalya","types":["administrative_area_level_1","political"]},{"long_name":"Turkey","short_name":"TR","types":["country","political"]},{"long_name":"07200","short_name":"07200","types":["postal_code"]}],"formatted_address":"Meydankavağı, 07200 Muratpaşa/Antalya, Turkey","geometry":{"bounds":{"northeast":{"lat":36.8884839,"lng":30.7399059},"southwest":{"lat":36.874612,"lng":30.722669}},"location":{"lat":36.8812349,"lng":30.7321211},"location_type":"APPROXIMATE","viewport":{"northeast":{"lat":36.8884839,"lng":30.7399059},"southwest":{"lat":36.874612,"lng":30.722669}}},"place_id":"ChIJ-1nH97SawxQRxlhoENPTaMI","types":["administrative_area_level_4","political"]}]