[{"address_components":[{"long_name":"Demirtaş","short_name":"Demirtaş","types":["administrative_area_level_4","political"]},{"long_name":"Alanya","short_name":"Alanya","types":["administrative_area_level_2","political"]},{"long_name":"Antalya","short_name":"Antalya","types":["administrative_area_level_1","political"]},{"long_name":"Turkey","short_name":"TR","types":["country","political"]}],"formatted_address":"Demirtaş, Alanya/Antalya, Turkey","geometry":{"bounds":{"northeast":{"lat":36.438441,"lng":32.2087171},"southwest":{"lat":36.410642,"lng":32.174683}},"location":{"lat":36.4218641,"lng":32.1916328},"location_type":"APPROXIMATE","viewport":{"northeast":{"lat":36.438441,"lng":32.2087171},"southwest":{"lat":36.410642,"lng":32.174683}}},"place_id":"ChIJEwDsi8-P3BQRnkHCHNXMNcs","types":["administrative_area_level_4","political"]}]