[{"address_components":[{"long_name":"Ağlasun","short_name":"Ağlasun","types":["administrative_area_level_2","political"]},{"long_name":"Burdur","short_name":"Burdur","types":["administrative_area_level_1","political"]},{"long_name":"Turkey","short_name":"TR","types":["country","political"]}],"formatted_address":"Ağlasun/Burdur, Turkey","geometry":{"bounds":{"northeast":{"lat":37.70072589999999,"lng":30.7740011},"southwest":{"lat":37.531197,"lng":30.46759}},"location":{"lat":37.6022375,"lng":30.5969758},"location_type":"APPROXIMATE","viewport":{"northeast":{"lat":37.70072589999999,"lng":30.7740011},"southwest":{"lat":37.531197,"lng":30.46759}}},"partial_match":true,"place_id":"ChIJw88XkABMxBQRBFzDBM6wi8E","types":["administrative_area_level_2","political"]}]