[{"address_components":[{"long_name":"Kulp","short_name":"Kulp","types":["locality","political"]},{"long_name":"Kulp","short_name":"Kulp","types":["administrative_area_level_2","political"]},{"long_name":"Diyarbakır","short_name":"Diyarbakır","types":["administrative_area_level_1","political"]},{"long_name":"Turkey","short_name":"TR","types":["country","political"]}],"formatted_address":"Kulp, Diyarbakır, Turkey","geometry":{"bounds":{"northeast":{"lat":38.504347,"lng":41.0177761},"southwest":{"lat":38.494073,"lng":41.005064}},"location":{"lat":38.500119,"lng":41.009861},"location_type":"APPROXIMATE","viewport":{"northeast":{"lat":38.504347,"lng":41.0177761},"southwest":{"lat":38.494073,"lng":41.005064}}},"place_id":"ChIJY4XUKixtc0ARk5DLXPh4qmI","types":["locality","political"]}]