[{"address_components":[{"long_name":"Abdullah Paşa","short_name":"Abdullah Paşa","types":["administrative_area_level_4","political"]},{"long_name":"Elâzığ Merkez","short_name":"Elâzığ Merkez","types":["administrative_area_level_2","political"]},{"long_name":"Elazığ","short_name":"Elazığ","types":["administrative_area_level_1","political"]},{"long_name":"Turkey","short_name":"TR","types":["country","political"]}],"formatted_address":"Abdullah Paşa, Elâzığ Merkez/Elazığ, Turkey","geometry":{"bounds":{"northeast":{"lat":38.669334,"lng":39.16126209999999},"southwest":{"lat":38.6471,"lng":39.129526}},"location":{"lat":38.659214,"lng":39.1481545},"location_type":"APPROXIMATE","viewport":{"northeast":{"lat":38.669334,"lng":39.16126209999999},"southwest":{"lat":38.6471,"lng":39.129526}}},"place_id":"ChIJ9QKwJ4bqdkARtMqNHXbuoPQ","types":["administrative_area_level_4","political"]}]