[{"address_components":[{"long_name":"Hakkâri Merkez","short_name":"Hakkâri Merkez","types":["administrative_area_level_2","political"]},{"long_name":"Hakkari","short_name":"Hakkari","types":["administrative_area_level_1","political"]},{"long_name":"Turkey","short_name":"TR","types":["country","political"]}],"formatted_address":"Hakkâri Merkez/Hakkari, Turkey","geometry":{"bounds":{"northeast":{"lat":37.8051731,"lng":44.092094},"southwest":{"lat":37.332045,"lng":43.3116549}},"location":{"lat":37.521741,"lng":43.7428063},"location_type":"APPROXIMATE","viewport":{"northeast":{"lat":37.8051731,"lng":44.092094},"southwest":{"lat":37.332045,"lng":43.3116549}}},"place_id":"ChIJI3_iqtoBD0ARgdl4013dMNQ","types":["administrative_area_level_2","political"]}]