[{"address_components":[{"long_name":"Atatürk","short_name":"Atatürk","types":["administrative_area_level_4","political"]},{"long_name":"Mezitli","short_name":"Mezitli","types":["administrative_area_level_2","political"]},{"long_name":"Mersin","short_name":"Mersin","types":["administrative_area_level_1","political"]},{"long_name":"Turkey","short_name":"TR","types":["country","political"]},{"long_name":"33340","short_name":"33340","types":["postal_code"]}],"formatted_address":"Atatürk, 33340 Mezitli/Mersin, Turkey","geometry":{"bounds":{"northeast":{"lat":36.76786,"lng":34.553498},"southwest":{"lat":36.75753,"lng":34.536977}},"location":{"lat":36.7645547,"lng":34.5459159},"location_type":"APPROXIMATE","viewport":{"northeast":{"lat":36.76786,"lng":34.553498},"southwest":{"lat":36.75753,"lng":34.536977}}},"place_id":"ChIJOw_x7eSKJxUR9lRN75WqjHA","types":["administrative_area_level_4","political"]}]