[{"address_components":[{"long_name":"Vefa","short_name":"Vefa","types":["bus_station","establishment","point_of_interest","transit_station"]},{"long_name":"Atatürk Bulvarı","short_name":"Atatürk Bulvarı","types":["route"]},{"long_name":"Fener Mahallesi","short_name":"Fener Mahallesi","types":["administrative_area_level_4","political"]},{"long_name":"Fatih","short_name":"Fatih","types":["administrative_area_level_3","political"]},{"long_name":"Fatih","short_name":"Fatih","types":["administrative_area_level_2","political"]},{"long_name":"İstanbul","short_name":"İstanbul","types":["administrative_area_level_1","political"]},{"long_name":"Turkey","short_name":"TR","types":["country","political"]},{"long_name":"34134","short_name":"34134","types":["postal_code"]}],"formatted_address":"Fener Mahallesi, Vefa, Atatürk Bulvarı, 34134 Fatih/İstanbul, Turkey","geometry":{"location":{"lat":41.0181908,"lng":28.9577658},"location_type":"GEOMETRIC_CENTER","viewport":{"northeast":{"lat":41.0195397802915,"lng":28.9591147802915},"southwest":{"lat":41.0168418197085,"lng":28.9564168197085}}},"place_id":"ChIJ1UZHTou5yhQRMVQvNc9oJ94","plus_code":{"compound_code":"2X95+74 Eminönü, Rüstem Paşa, Fatih/İstanbul, Turkey","global_code":"8GHC2X95+74"},"types":["bus_station","establishment","point_of_interest","transit_station"]}]