[{"address_components":[{"long_name":"Yeşilköy","short_name":"Yeşilköy","types":["administrative_area_level_4","political"]},{"long_name":"Bakırköy","short_name":"Bakırköy","types":["administrative_area_level_2","political"]},{"long_name":"İstanbul","short_name":"İstanbul","types":["administrative_area_level_1","political"]},{"long_name":"Turkey","short_name":"TR","types":["country","political"]}],"formatted_address":"Yeşilköy, Bakırköy/İstanbul, Turkey","geometry":{"bounds":{"northeast":{"lat":41.000703,"lng":28.847164},"southwest":{"lat":40.954508,"lng":28.7969681}},"location":{"lat":40.9776484,"lng":28.8188948},"location_type":"APPROXIMATE","viewport":{"northeast":{"lat":41.000703,"lng":28.847164},"southwest":{"lat":40.954508,"lng":28.7969681}}},"place_id":"ChIJKUJszA2jyhQRCg7Srl6-SmE","types":["administrative_area_level_4","political"]}]