[{"address_components":[{"long_name":"Güneşli","short_name":"Güneşli","types":["administrative_area_level_4","political"]},{"long_name":"Bağcılar","short_name":"Bağcılar","types":["administrative_area_level_2","political"]},{"long_name":"İstanbul","short_name":"İstanbul","types":["administrative_area_level_1","political"]},{"long_name":"Turkey","short_name":"TR","types":["country","political"]},{"long_name":"34100","short_name":"34100","types":["postal_code"]}],"formatted_address":"Güneşli, 34100 Bağcılar/İstanbul, Turkey","geometry":{"bounds":{"northeast":{"lat":41.0454821,"lng":28.834427},"southwest":{"lat":41.030978,"lng":28.8228269}},"location":{"lat":41.0386605,"lng":28.8290922},"location_type":"APPROXIMATE","viewport":{"northeast":{"lat":41.0454821,"lng":28.834427},"southwest":{"lat":41.030978,"lng":28.8228269}}},"place_id":"ChIJY4uMRRylyhQRmoxuT7dnUL4","types":["administrative_area_level_4","political"]}]