[{"address_components":[{"long_name":"Yıldıztabya","short_name":"Yıldıztabya","types":["administrative_area_level_4","political"]},{"long_name":"Gaziosmanpaşa","short_name":"Gaziosmanpaşa","types":["administrative_area_level_2","political"]},{"long_name":"İstanbul","short_name":"İstanbul","types":["administrative_area_level_1","political"]},{"long_name":"Turkey","short_name":"TR","types":["country","political"]},{"long_name":"34240","short_name":"34240","types":["postal_code"]}],"formatted_address":"Yıldıztabya, 34240 Gaziosmanpaşa/İstanbul, Turkey","geometry":{"bounds":{"northeast":{"lat":41.0697819,"lng":28.936361},"southwest":{"lat":41.060987,"lng":28.922256}},"location":{"lat":41.0649058,"lng":28.9281179},"location_type":"APPROXIMATE","viewport":{"northeast":{"lat":41.0697819,"lng":28.936361},"southwest":{"lat":41.060987,"lng":28.922256}}},"place_id":"ChIJ_0zAg-qwyhQR5hyxHRao1is","types":["administrative_area_level_4","political"]}]