[{"address_components":[{"long_name":"Cumhuriyet","short_name":"Cumhuriyet","types":["administrative_area_level_4","political"]},{"long_name":"Şişli","short_name":"Şişli","types":["administrative_area_level_2","political"]},{"long_name":"İstanbul","short_name":"İstanbul","types":["administrative_area_level_1","political"]},{"long_name":"Turkey","short_name":"TR","types":["country","political"]},{"long_name":"34380","short_name":"34380","types":["postal_code"]}],"formatted_address":"Cumhuriyet, 34380 Şişli/İstanbul, Turkey","geometry":{"bounds":{"northeast":{"lat":41.059323,"lng":28.98755},"southwest":{"lat":41.051206,"lng":28.9743599}},"location":{"lat":41.0551587,"lng":28.9827008},"location_type":"APPROXIMATE","viewport":{"northeast":{"lat":41.059323,"lng":28.98755},"southwest":{"lat":41.051206,"lng":28.9743599}}},"place_id":"ChIJF5dw4Fy1yhQRrMCJtkTG91k","types":["administrative_area_level_4","political"]}]