[{"address_components":[{"long_name":"Altınşehir","short_name":"Altınşehir","types":["administrative_area_level_4","political"]},{"long_name":"Başakşehir","short_name":"Başakşehir","types":["administrative_area_level_2","political"]},{"long_name":"İstanbul","short_name":"İstanbul","types":["administrative_area_level_1","political"]},{"long_name":"Turkey","short_name":"TR","types":["country","political"]},{"long_name":"34494","short_name":"34494","types":["postal_code"]}],"formatted_address":"Altınşehir, 34494 Başakşehir/İstanbul, Turkey","geometry":{"bounds":{"northeast":{"lat":41.0744411,"lng":28.7594109},"southwest":{"lat":41.060963,"lng":28.742768}},"location":{"lat":41.0693768,"lng":28.7460373},"location_type":"APPROXIMATE","viewport":{"northeast":{"lat":41.0744411,"lng":28.7594109},"southwest":{"lat":41.060963,"lng":28.742768}}},"place_id":"ChIJuQoTjmimyhQRRI7dy8tx19w","types":["administrative_area_level_4","political"]}]