[{"address_components":[{"long_name":"Çatalca","short_name":"Çatalca","types":["locality","political"]},{"long_name":"Çatalca","short_name":"Çatalca","types":["administrative_area_level_2","political"]},{"long_name":"İstanbul","short_name":"İstanbul","types":["administrative_area_level_1","political"]},{"long_name":"Turkey","short_name":"TR","types":["country","political"]}],"formatted_address":"Çatalca, İstanbul, Turkey","geometry":{"bounds":{"northeast":{"lat":41.1660391,"lng":28.4916331},"southwest":{"lat":41.125505,"lng":28.431541}},"location":{"lat":41.142259,"lng":28.457469},"location_type":"APPROXIMATE","viewport":{"northeast":{"lat":41.1660391,"lng":28.4916331},"southwest":{"lat":41.125505,"lng":28.431541}}},"place_id":"ChIJpVw6wT5FtRQRgc3ShJNNjb8","types":["locality","political"]}]