[{"address_components":[{"long_name":"Çubuklu","short_name":"Çubuklu","types":["administrative_area_level_4","political"]},{"long_name":"Beykoz","short_name":"Beykoz","types":["administrative_area_level_2","political"]},{"long_name":"İstanbul","short_name":"İstanbul","types":["administrative_area_level_1","political"]},{"long_name":"Turkey","short_name":"TR","types":["country","political"]},{"long_name":"34805","short_name":"34805","types":["postal_code"]}],"formatted_address":"Çubuklu, 34805 Beykoz/İstanbul, Turkey","geometry":{"bounds":{"northeast":{"lat":41.11029509999999,"lng":29.102317},"southwest":{"lat":41.0943871,"lng":29.07134899999999}},"location":{"lat":41.1019844,"lng":29.0838099},"location_type":"APPROXIMATE","viewport":{"northeast":{"lat":41.11029509999999,"lng":29.102317},"southwest":{"lat":41.0943871,"lng":29.07134899999999}}},"place_id":"ChIJE_dx4E3KyhQRRA88KzDFaHo","types":["administrative_area_level_4","political"]}]