[{"address_components":[{"long_name":"Gürçeşme Caddesi","short_name":"Gürçeşme Cd.","types":["route"]},{"long_name":"Konak","short_name":"Konak","types":["administrative_area_level_2","political"]},{"long_name":"İzmir","short_name":"İzmir","types":["administrative_area_level_1","political"]},{"long_name":"Turkey","short_name":"TR","types":["country","political"]},{"long_name":"35360","short_name":"35360","types":["postal_code"]}],"formatted_address":"Gürçeşme Cd., 35360 Konak/İzmir, Turkey","geometry":{"bounds":{"northeast":{"lat":38.4233801,"lng":27.1617685},"southwest":{"lat":38.4037332,"lng":27.1511077}},"location":{"lat":38.4149462,"lng":27.1601256},"location_type":"GEOMETRIC_CENTER","viewport":{"northeast":{"lat":38.4233801,"lng":27.1617685},"southwest":{"lat":38.4037332,"lng":27.1511077}}},"place_id":"ChIJxZRPeZHYuxQRHhwG020tR-8","types":["route"]}]