[{"address_components":[{"long_name":"Seydişehir","short_name":"Seydişehir","types":["locality","political"]},{"long_name":"Seydişehir","short_name":"Seydişehir","types":["administrative_area_level_2","political"]},{"long_name":"Konya","short_name":"Konya","types":["administrative_area_level_1","political"]},{"long_name":"Turkey","short_name":"TR","types":["country","political"]}],"formatted_address":"Seydişehir, Konya, Turkey","geometry":{"bounds":{"northeast":{"lat":37.449391,"lng":31.88624909999999},"southwest":{"lat":37.392205,"lng":31.8201149}},"location":{"lat":37.41926,"lng":31.848216},"location_type":"APPROXIMATE","viewport":{"northeast":{"lat":37.449391,"lng":31.88624909999999},"southwest":{"lat":37.392205,"lng":31.8201149}}},"place_id":"ChIJ8ZKDkzDa2hQRYDHXUbGdJxY","types":["locality","political"]}]