[{"address_components":[{"long_name":"Kumkuyucak","short_name":"Kumkuyucak","types":["locality","political"]},{"long_name":"Kumkuyucak","short_name":"Kumkuyucak","types":["administrative_area_level_4","political"]},{"long_name":"Saruhanlı","short_name":"Saruhanlı","types":["administrative_area_level_2","political"]},{"long_name":"Manisa","short_name":"Manisa","types":["administrative_area_level_1","political"]},{"long_name":"Turkey","short_name":"TR","types":["country","political"]},{"long_name":"45800","short_name":"45800","types":["postal_code"]}],"formatted_address":"Kumkuyucak, 45800 Saruhanlı/Manisa, Turkey","geometry":{"location":{"lat":38.74704,"lng":27.824969},"location_type":"APPROXIMATE","viewport":{"northeast":{"lat":38.7557418,"lng":27.8409764},"southwest":{"lat":38.7383372,"lng":27.8089616}}},"place_id":"ChIJyZu65Qu2uRQRTMwrQ6zPxMo","types":["locality","political"]}]