[{"address_components":[{"long_name":"Aktuzla","short_name":"Aktuzla","types":["locality","political"]},{"long_name":"Dedeağaç","short_name":"Dedeağaç","types":["administrative_area_level_4","political"]},{"long_name":"Yapraklı","short_name":"Yapraklı","types":["administrative_area_level_3","political"]},{"long_name":"Malazgirt","short_name":"Malazgirt","types":["administrative_area_level_2","political"]},{"long_name":"Muş","short_name":"Muş","types":["administrative_area_level_1","political"]},{"long_name":"Turkey","short_name":"TR","types":["country","political"]},{"long_name":"49420","short_name":"49420","types":["postal_code"]}],"formatted_address":"Aktuzla, Dedeağaç, 49420 Yapraklı/Malazgirt/Muş, Turkey","geometry":{"location":{"lat":39.338619,"lng":42.29869799999999},"location_type":"APPROXIMATE","viewport":{"northeast":{"lat":39.3472482,"lng":42.3147054},"southwest":{"lat":39.3299887,"lng":42.2826906}}},"place_id":"ChIJoz9P6BsGbUARNKOWINhZb_Y","types":["locality","political"]}]