[{"address_components":[{"long_name":"Avanos","short_name":"Avanos","types":["locality","political"]},{"long_name":"Avanos","short_name":"Avanos","types":["administrative_area_level_2","political"]},{"long_name":"Nevşehir","short_name":"Nevşehir","types":["administrative_area_level_1","political"]},{"long_name":"Turkey","short_name":"TR","types":["country","political"]}],"formatted_address":"Avanos, Nevşehir, Turkey","geometry":{"bounds":{"northeast":{"lat":38.72819,"lng":34.8662969},"southwest":{"lat":38.6991551,"lng":34.8230939}},"location":{"lat":38.71081400000001,"lng":34.842081},"location_type":"APPROXIMATE","viewport":{"northeast":{"lat":38.72819,"lng":34.8662969},"southwest":{"lat":38.6991551,"lng":34.8230939}}},"partial_match":true,"place_id":"ChIJZT2AorJgKhURF8KN6HHw1FQ","types":["locality","political"]}]