[{"address_components":[{"long_name":"Serdivan","short_name":"Serdivan","types":["political","sublocality","sublocality_level_1"]},{"long_name":"Serdivan","short_name":"Serdivan","types":["administrative_area_level_2","political"]},{"long_name":"Sakarya","short_name":"Sakarya","types":["administrative_area_level_1","political"]},{"long_name":"Turkey","short_name":"TR","types":["country","political"]}],"formatted_address":"Serdivan, Sakarya, Turkey","geometry":{"bounds":{"northeast":{"lat":40.7430343,"lng":30.3668299},"southwest":{"lat":40.734084,"lng":30.3424666}},"location":{"lat":40.7380582,"lng":30.3510005},"location_type":"APPROXIMATE","viewport":{"northeast":{"lat":40.7430343,"lng":30.3668299},"southwest":{"lat":40.734084,"lng":30.3424666}}},"place_id":"ChIJrSq3wJGyzBQRgBZMZ91J7G8","types":["political","sublocality","sublocality_level_1"]}]