[{"address_components":[{"long_name":"Koyulhisar","short_name":"Koyulhisar","types":["locality","political"]},{"long_name":"Koyulhisar","short_name":"Koyulhisar","types":["administrative_area_level_2","political"]},{"long_name":"Sivas","short_name":"Sivas","types":["administrative_area_level_1","political"]},{"long_name":"Turkey","short_name":"TR","types":["country","political"]}],"formatted_address":"Koyulhisar, Sivas, Turkey","geometry":{"bounds":{"northeast":{"lat":40.30670600000001,"lng":37.8365831},"southwest":{"lat":40.287388,"lng":37.8207799}},"location":{"lat":40.301538,"lng":37.832185},"location_type":"APPROXIMATE","viewport":{"northeast":{"lat":40.30670600000001,"lng":37.8365831},"southwest":{"lat":40.287388,"lng":37.8207799}}},"partial_match":true,"place_id":"ChIJ2Ubp5DScfEARS3zERr0_eBU","types":["locality","political"]}]