[{"address_components":[{"long_name":"Silahtarağa","short_name":"Silahtarağa","types":["administrative_area_level_4","political"]},{"long_name":"Çorlu","short_name":"Çorlu","types":["administrative_area_level_2","political"]},{"long_name":"Tekirdağ","short_name":"Tekirdağ","types":["administrative_area_level_1","political"]},{"long_name":"Turkey","short_name":"TR","types":["country","political"]}],"formatted_address":"Silahtarağa, Çorlu/Tekirdağ, Turkey","geometry":{"bounds":{"northeast":{"lat":41.194267,"lng":27.8336149},"southwest":{"lat":41.1675389,"lng":27.800146}},"location":{"lat":41.180929,"lng":27.8223506},"location_type":"APPROXIMATE","viewport":{"northeast":{"lat":41.194267,"lng":27.8336149},"southwest":{"lat":41.1675389,"lng":27.800146}}},"place_id":"ChIJ6awLvD_ntBQRqtoLsxxK32Q","types":["administrative_area_level_4","political"]}]