[{"address_components":[{"long_name":"Tokat Merkez","short_name":"Tokat Merkez","types":["administrative_area_level_2","political"]},{"long_name":"Tokat","short_name":"Tokat","types":["administrative_area_level_1","political"]},{"long_name":"Turkey","short_name":"TR","types":["country","political"]}],"formatted_address":"Tokat Merkez/Tokat, Turkey","geometry":{"bounds":{"northeast":{"lat":40.560479,"lng":36.9154719},"southwest":{"lat":39.962289,"lng":36.3394319}},"location":{"lat":40.3000971,"lng":36.5590413},"location_type":"APPROXIMATE","viewport":{"northeast":{"lat":40.560479,"lng":36.9154719},"southwest":{"lat":39.962289,"lng":36.3394319}}},"partial_match":true,"place_id":"ChIJD2z-Y6O1fUARHsm8bLIRP4U","types":["administrative_area_level_2","political"]}]