[{"address_components":[{"long_name":"Karahallı","short_name":"Karahallı","types":["locality","political"]},{"long_name":"Karahallı","short_name":"Karahallı","types":["administrative_area_level_2","political"]},{"long_name":"Uşak","short_name":"Uşak","types":["administrative_area_level_1","political"]},{"long_name":"Turkey","short_name":"TR","types":["country","political"]}],"formatted_address":"Karahallı, Uşak, Turkey","geometry":{"bounds":{"northeast":{"lat":38.326149,"lng":29.54247389999999},"southwest":{"lat":38.314634,"lng":29.5232881}},"location":{"lat":38.319945,"lng":29.531498},"location_type":"APPROXIMATE","viewport":{"northeast":{"lat":38.326149,"lng":29.54247389999999},"southwest":{"lat":38.314634,"lng":29.5232881}}},"place_id":"ChIJoVb_vxU2xhQRdZDLoPqGa1Q","types":["locality","political"]}]