[{"address_components":[{"long_name":"Toprakkale","short_name":"Toprakkale","types":["locality","political"]},{"long_name":"Toprakkale","short_name":"Toprakkale","types":["administrative_area_level_2","political"]},{"long_name":"Osmaniye","short_name":"Osmaniye","types":["administrative_area_level_1","political"]},{"long_name":"Turkey","short_name":"TR","types":["country","political"]}],"formatted_address":"Toprakkale, Osmaniye, Turkey","geometry":{"bounds":{"northeast":{"lat":37.076065,"lng":36.1969768},"southwest":{"lat":37.039914,"lng":36.126318}},"location":{"lat":37.062415,"lng":36.145216},"location_type":"APPROXIMATE","viewport":{"northeast":{"lat":37.076065,"lng":36.1969768},"southwest":{"lat":37.039914,"lng":36.126318}}},"place_id":"ChIJ2erqFCQkLxURpKuczl68-do","types":["locality","political"]}]