[{"address_components":[{"long_name":"Kalıcı Konutlar Yolu","short_name":"Kalıcı Konutlar Yolu","types":["route"]},{"long_name":"Düzce Merkez","short_name":"Düzce Merkez","types":["administrative_area_level_2","political"]},{"long_name":"Düzce","short_name":"Düzce","types":["administrative_area_level_1","political"]},{"long_name":"Turkey","short_name":"TR","types":["country","political"]}],"formatted_address":"Kalıcı Konutlar Yolu, Düzce Merkez/Düzce, Turkey","geometry":{"bounds":{"northeast":{"lat":40.8876252,"lng":31.1976953},"southwest":{"lat":40.8801792,"lng":31.18792669999999}},"location":{"lat":40.8844952,"lng":31.1908949},"location_type":"GEOMETRIC_CENTER","viewport":{"northeast":{"lat":40.8876252,"lng":31.1976953},"southwest":{"lat":40.8801792,"lng":31.18792669999999}}},"place_id":"ChIJn623c4SgnUARt5R0JnDcl3s","types":["route"]}]